flake8_noqa/__init__.py
flake8_noqa/noqa_checker.py
flake8_noqa/noqa_comment.py
flake8_noqa/noqa_filter.py
flake8_noqa-1.4.0.dist-info/COPYING.LESSER
flake8_noqa-1.4.0.dist-info/LICENSE
flake8_noqa-1.4.0.dist-info/METADATA
flake8_noqa-1.4.0.dist-info/WHEEL
flake8_noqa-1.4.0.dist-info/entry_points.txt
flake8_noqa-1.4.0.dist-info/top_level.txt
flake8_noqa-1.4.0.dist-info/RECORD
